azuredevops_tools/__init__.py
azuredevops_tools/devops_tools.py
azuredevops_tools/main.py
azuredevops_tools/tools.py
azuredevops_tools-0.3.0.dist-info/METADATA
azuredevops_tools-0.3.0.dist-info/WHEEL
azuredevops_tools-0.3.0.dist-info/entry_points.txt
azuredevops_tools-0.3.0.dist-info/licenses/LICENSE
azuredevops_tools-0.3.0.dist-info/RECORD
