Metadata-Version: 2.4
Name: azuredevops-tools
Version: 0.3.0
Summary: Comprehensive Azure DevOps Tools for Model Context Protocol (MCP) integration including Git repositories, pull requests, builds, changesets, and approval workflows
Project-URL: Homepage, https://github.com/mafzaal/azuredevops-tools
Project-URL: Repository, https://github.com/mafzaal/azuredevops-tools
Project-URL: Issues, https://github.com/mafzaal/azuredevops-tools/issues
Author-email: Muhammad Afzaal <mo@thedataguy.pro>
License-File: LICENSE
Classifier: Development Status :: 4 - Beta
Classifier: Intended Audience :: Developers
Classifier: License :: OSI Approved :: MIT License
Classifier: Programming Language :: Python :: 3.11
Classifier: Programming Language :: Python :: 3.12
Classifier: Programming Language :: Python :: 3.13
Requires-Python: >=3.11
Requires-Dist: azure-devops>=7.1.0b4
Requires-Dist: mcp[cli]>=1.9.2
Requires-Dist: python-dotenv>=1.1.0
Provides-Extra: dev
Requires-Dist: black>=22.0; extra == 'dev'
Requires-Dist: flake8>=4.0; extra == 'dev'
Requires-Dist: isort>=5.0; extra == 'dev'
Requires-Dist: pytest-cov>=4.0; extra == 'dev'
Requires-Dist: pytest>=7.0; extra == 'dev'
